RsCmwDau/RsCmwDau.py
RsCmwDau/__init__.py
RsCmwDau/enums.py
RsCmwDau/repcap.py
RsCmwDau/CustomFiles/__init__.py
RsCmwDau/CustomFiles/events.py
RsCmwDau/CustomFiles/reliability.py
RsCmwDau/CustomFiles/utilities.py
RsCmwDau/Implementations/Configure.py
RsCmwDau/Implementations/Data.py
RsCmwDau/Implementations/Rdau.py
RsCmwDau/Implementations/Sense.py
RsCmwDau/Implementations/Source.py
RsCmwDau/Implementations/__init__.py
RsCmwDau/Implementations/Configure_/Data.py
RsCmwDau/Implementations/Configure_/Switch.py
RsCmwDau/Implementations/Configure_/__init__.py
RsCmwDau/Implementations/Configure_/Data_/Control.py
RsCmwDau/Implementations/Configure_/Data_/Measurement.py
RsCmwDau/Implementations/Configure_/Data_/__init__.py
RsCmwDau/Implementations/Configure_/Data_/Control_/Advanced.py
RsCmwDau/Implementations/Configure_/Data_/Control_/Deploy.py
RsCmwDau/Implementations/Configure_/Data_/Control_/Dns.py
RsCmwDau/Implementations/Configure_/Data_/Control_/Epdg.py
RsCmwDau/Implementations/Configure_/Data_/Control_/Ftp.py
RsCmwDau/Implementations/Configure_/Data_/Control_/Http.py
RsCmwDau/Implementations/Configure_/Data_/Control_/Ims.py
RsCmwDau/Implementations/Configure_/Data_/Control_/IpvFour.py
RsCmwDau/Implementations/Configure_/Data_/Control_/IpvSix.py
RsCmwDau/Implementations/Configure_/Data_/Control_/Supl.py
RsCmwDau/Implementations/Configure_/Data_/Control_/Udp.py
RsCmwDau/Implementations/Configure_/Data_/Control_/__init__.py
RsCmwDau/Implementations/Configure_/Data_/Control_/Dns_/Aservices.py
RsCmwDau/Implementations/Configure_/Data_/Control_/Dns_/Foreign.py
RsCmwDau/Implementations/Configure_/Data_/Control_/Dns_/Local.py
RsCmwDau/Implementations/Configure_/Data_/Control_/Dns_/Primary.py
RsCmwDau/Implementations/Configure_/Data_/Control_/Dns_/Secondary.py
RsCmwDau/Implementations/Configure_/Data_/Control_/Dns_/Test.py
RsCmwDau/Implementations/Configure_/Data_/Control_/Dns_/__init__.py
RsCmwDau/Implementations/Configure_/Data_/Control_/Dns_/Aservices_/Add.py
RsCmwDau-3.7.51.26.dist-info/METADATA
RsCmwDau-3.7.51.26.dist-info/WHEEL
RsCmwDau-3.7.51.26.dist-info/top_level.txt
RsCmwDau-3.7.51.26.dist-info/RECORD
