Metadata-Version: 2.1
Name: RsCmwDau
Version: 3.7.51.26
Summary: CMW Data Application Unit Remote-control Module
Home-page: UNKNOWN
Author: Rohde & Schwarz GmbH & Co. KG
Author-email: Customer.Support@rohde-schwarz.com
License: MIT
Platform: UNKNOWN
Classifier: License :: OSI Approved :: MIT License
Classifier: Programming Language :: Python :: 3.6
Requires-Dist: PyVisa
